aad_fastapi/__init__.py
aad_fastapi/aad_auth_error.py
aad_fastapi/aad_bearer_backend.py
aad_fastapi/aad_decorators.py
aad_fastapi/aad_discover_keys.py
aad_fastapi/aad_helpers.py
aad_fastapi/aad_options.py
aad_fastapi/aad_token.py
aad_fastapi/aad_user.py
aad_fastapi/aad_vault.py
aad_fastapi/base.py
aad_fastapi/roles/__init__.py
aad_fastapi/roles/all_role_validator.py
aad_fastapi/roles/any_role_validator.py
aad_fastapi/roles/role_requirement.py
aad_fastapi/roles/role_validator.py
aad_fastapi/roles/role_validator_interface.py
aad_fastapi-1.1.5.dist-info/LICENSE
aad_fastapi-1.1.5.dist-info/METADATA
aad_fastapi-1.1.5.dist-info/WHEEL
aad_fastapi-1.1.5.dist-info/top_level.txt
aad_fastapi-1.1.5.dist-info/RECORD
