Metadata-Version: 2.1
Name: aad_fastapi
Version: 1.1.5
Summary: aad_fastapi middleware backend helper for bearer verification with FastAPI and Azure AD
Home-page: https://github.com/Mimetis/aad_fastapi
Author: Sébastien Pertus, Dor Lugasi-Gal
Author-email: sebastien.pertus@gmail.com, dorlugasigal@gmail.com
Project-URL: Homepage, https://github.com/Mimetis/aad_fastapi
Project-URL: Bug Tracker, https://github.com/Mimetis/aad_fastapi/issues
Keywords: python
Classifier: Programming Language :: Python :: 3
Classifier: License :: OSI Approved :: MIT License
Classifier: Operating System :: OS Independent
Requires-Python: >=3.7
License-File: LICENSE
Requires-Dist: Authlib
Requires-Dist: msal
Requires-Dist: azure-identity
Requires-Dist: azure-keyvault
Requires-Dist: azure-keyvault-certificates
Requires-Dist: fastapi[all]
Requires-Dist: aiohttp
Requires-Dist: async-asgi-testclient
Requires-Dist: multidict
Provides-Extra: test
Requires-Dist: pytest; extra == "test"
Requires-Dist: coverage; extra == "test"
Requires-Dist: flake8; extra == "test"
Requires-Dist: black; extra == "test"
Requires-Dist: isort; extra == "test"
Requires-Dist: pytest-cov; extra == "test"
Requires-Dist: codecov; extra == "test"
Requires-Dist: gitchangelog; extra == "test"
Requires-Dist: mkdocs; extra == "test"
Requires-Dist: Authlib; extra == "test"
Requires-Dist: msal; extra == "test"
Requires-Dist: azure-identity; extra == "test"
Requires-Dist: azure-keyvault; extra == "test"
Requires-Dist: azure-keyvault-certificates; extra == "test"
Requires-Dist: fastapi[all]; extra == "test"
Requires-Dist: aiohttp; extra == "test"
Requires-Dist: async-asgi-testclient; extra == "test"
Requires-Dist: pytest-asyncio; extra == "test"
